siigo_mcp/__init__.py
siigo_mcp/auth.py
siigo_mcp/client.py
siigo_mcp/server.py
siigo_mcp/resources/__init__.py
siigo_mcp/tools/__init__.py
siigo_mcp/tools/credit_notes.py
siigo_mcp/tools/customers.py
siigo_mcp/tools/discovery.py
siigo_mcp/tools/invoices.py
siigo_mcp/tools/journals.py
siigo_mcp/tools/products.py
siigo_mcp/tools/reference.py
siigo_mcp-0.1.2.dist-info/licenses/LICENSE
siigo_mcp-0.1.2.dist-info/METADATA
siigo_mcp-0.1.2.dist-info/WHEEL
siigo_mcp-0.1.2.dist-info/entry_points.txt
siigo_mcp-0.1.2.dist-info/top_level.txt
siigo_mcp-0.1.2.dist-info/RECORD
