Metadata-Version: 2.4
Name: siigo-mcp
Version: 0.1.2
Summary: MCP server for Siigo invoicing software
Author-email: David Sanchez <64162682+dsfaccini@users.noreply.github.com>
License-Expression: MIT
Project-URL: Homepage, https://github.com/dsfaccini/siigo-mcp
Project-URL: Repository, https://github.com/dsfaccini/siigo-mcp
Project-URL: Issues, https://github.com/dsfaccini/siigo-mcp/issues
Project-URL: Twitter, https://twitter.com/dasfacc
Keywords: mcp,siigo,invoicing,colombia,facturacion-electronica
Classifier: Development Status :: 4 - Beta
Classifier: Intended Audience :: Developers
Classifier: Programming Language :: Python :: 3.13
Classifier: Topic :: Office/Business :: Financial :: Accounting
Requires-Python: >=3.13
License-File: LICENSE
Requires-Dist: fastmcp>=2.14.1
Requires-Dist: httpx>=0.28.1
Requires-Dist: logfire>=4.16.0
Requires-Dist: pydantic>=2.12.5
Dynamic: license-file
